spdist-0.1.3.dist-info/METADATA
spdist-0.1.3.dist-info/WHEEL
spdist/__init__.py
spdist/__init__.pyi
spdist/py.typed
spdist/spdist.pypy39-pp73-ppc_64-linux-gnu.so
spdist-0.1.3.dist-info/RECORD
